stone_lib/__init__.py
stone_lib/analyser/__init__.py
stone_lib/analyser/pytorch/__init__.py
stone_lib/analyser/pytorch/model_summary.py
stone_lib/analyser/pytorch/profiler/__init__.py
stone_lib/analyser/pytorch/profiler/memoy.py
stone_lib/analyser/pytorch/profiler/node.py
stone_lib/analyser/pytorch/profiler/ops.py
stone_lib/analyser/pytorch/profiler/readme.md
stone_lib/analyser/pytorch/profiler/stack.py
stone_lib/data_structure/__init__.py
stone_lib/data_structure/bi_directional_links.py
stone_lib/data_structure/memory.py
stone_lib/data_structure/tree.py
stone_lib/logging.py
stone_lib/obsidian/__init__.py
stone_lib/obsidian/body.py
stone_lib/obsidian/metadata.py
stone_lib/obsidian/note.py
stone_lib/research/__init__.py
stone_lib/research/experimental_results/__init__.py
stone_lib/research/experimental_results/result_location.py
stone_lib/research/trace_data/__init__.py
stone_lib/research/trace_data/alibaba_gpu_2020.py
stone_lib/resource/__init__.py
stone_lib/resource/monitor/__init__.py
stone_lib/resource/monitor/cgroup.py
stone_lib/resource/monitor/ethernet.py
stone_lib/resource/monitor/host_monitor.py
stone_lib/resource/monitor/nvml.py
stone_lib/utilis/__init__.py
stone_lib/utilis/diagram.py
stone_lib/utilis/enum.py
stone_lib/utilis/network.py
stone_lib/utilis/utilis.py
stone_lib-0.11.1.dist-info/METADATA
stone_lib-0.11.1.dist-info/WHEEL
stone_lib-0.11.1.dist-info/RECORD
